lntime/__init__.py
lntime/common.py
lntime-1.0.1.dist-info/METADATA
lntime-1.0.1.dist-info/WHEEL
lntime-1.0.1.dist-info/top_level.txt
lntime-1.0.1.dist-info/RECORD
