Metadata-Version: 2.1
Name: lntime
Version: 1.0.1
Summary: extract Time
Home-page: https://github.com/lanmengfei/testdm
Author: lannan
Author-email: 865377886@qq.com
License: UNKNOWN
Platform: UNKNOWN
Classifier: Environment :: Web Environment
Classifier: Intended Audience :: Developers
Classifier: Operating System :: OS Independent
Classifier: Topic :: Text Processing :: Indexing
Classifier: Topic :: Utilities
Classifier: Topic :: Internet
Classifier: Topic :: Software Development :: Libraries :: Python Modules
Classifier: Programming Language :: Python
Classifier: Programming Language :: Python :: 3
Classifier: Programming Language :: Python :: 3.5
Requires-Dist: pandas (>=0.13)
Requires-Dist: beautifulsoup4 (>=4.6.3)
Requires-Dist: cx-Oracle
Requires-Dist: numpy
Requires-Dist: psycopg2-binary
Requires-Dist: selenium
Requires-Dist: xlsxwriter
Requires-Dist: xlrd
Requires-Dist: requests
Requires-Dist: lxml
Requires-Dist: sqlalchemy
Requires-Dist: pymssql
Requires-Dist: jieba
Requires-Dist: mysqlclient
Requires-Dist: openpyxl
Requires-Dist: lmf
